LICENSE.md
MANIFEST.in
README.md
setup.py
margray_2d/__init__.py
margray_2d/_sprite.py
margray_2d/_sprite_group.py
margray_2d/animated_sprite.py
margray_2d/animated_text.py
margray_2d/background.py
margray_2d/button.py
margray_2d/circle_sprite.py
margray_2d/constants.py
margray_2d/events.py
margray_2d/fps.py
margray_2d/healthbar.py
margray_2d/image.py
margray_2d/imbutton.py
margray_2d/imsprite.py
margray_2d/keys.py
margray_2d/main.py
margray_2d/mouse.py
margray_2d/player.py
margray_2d/player_test.py
margray_2d/scrolling_bg.py
margray_2d/sound.py
margray_2d/square_sprite.py
margray_2d/text.py
margray_2d/time.py
margray_2d/transparent_sprite.py
margray_2d/log_components/__init__.py
margray_2d/log_components/clr_win32/__init__.py
margray_2d/log_components/clr_win32/ansi.py
margray_2d/log_components/clr_win32/ansitowin32.py
margray_2d/log_components/clr_win32/initialise.py
margray_2d/log_components/clr_win32/win32.py
margray_2d/log_components/clr_win32/winterm.py
mrgr2d.egg-info/PKG-INFO
mrgr2d.egg-info/SOURCES.txt
mrgr2d.egg-info/dependency_links.txt
mrgr2d.egg-info/requires.txt
mrgr2d.egg-info/top_level.txt