Metadata-Version: 2.1
Name: mrgr2d
Version: 0.8
Summary: Margray 2D a library based on Pygame for Game Development
Home-page: https://margrayengine.github.io/
Author: AbdulWahab
License: MIT
Keywords: 2d,game
Platform: UNKNOWN
Classifier: License :: OSI Approved :: MIT License
Classifier: Development Status :: 4 - Beta
Classifier: Intended Audience :: Developers
Classifier: Programming Language :: Python :: 3
License-File: LICENSE.md
